AIMM_simulator/AIMM_simulator.py
AIMM_simulator/InH_pathloss_model.py
AIMM_simulator/NR_5G_standard_functions.py
AIMM_simulator/UMa_pathloss_model.py
AIMM_simulator/UMi_pathloss_model.py
AIMM_simulator/__init__.py
AIMM_simulator/fig_timestamp.py
AIMM_simulator/geometry_3d.py
AIMM_simulator/img/UMa_pathloss_model_01.pdf
aimm_simulator-2.0.3.dist-info/METADATA
aimm_simulator-2.0.3.dist-info/WHEEL
aimm_simulator-2.0.3.dist-info/licenses/LICENSE
aimm_simulator-2.0.3.dist-info/RECORD
