Metadata-Version: 2.1
Name: AIMM_simulator
Version: 2.0.3
Summary: AIMM 5G system-level simulator (development for the AIMM project https://aimm.celticnext.eu)
Project-URL: homepage, https://github.com/keithbriggs/AIMM-simulator
Project-URL: documentation, https://aimm-simulator.readthedocs.io/en/latest/
Author-email: Keith Briggs <k.briggs73@btinternet.com>
License-File: LICENSE
Keywords: 5G,cellular radio,simulation
Classifier: License :: OSI Approved :: MIT License
Classifier: Operating System :: OS Independent
Classifier: Programming Language :: Python :: 3
Requires-Python: >=3.8
Requires-Dist: matplotlib>=3.6
Requires-Dist: numpy>=1.23
Requires-Dist: simpy>=4.0
